ssh_wait/__init__.py
ssh_wait/__main__.py
ssh_wait-1.0.3.dist-info/licenses/LICENSE
ssh_wait-1.0.3.dist-info/METADATA
ssh_wait-1.0.3.dist-info/WHEEL
ssh_wait-1.0.3.dist-info/entry_points.txt
ssh_wait-1.0.3.dist-info/top_level.txt
ssh_wait-1.0.3.dist-info/RECORD
