Metadata-Version: 2.4
Name: ssh-wait
Version: 1.0.3
Summary: ssh-wait waits for the service to be available over ssh
Author-email: Barry Scott <barry@barrys-emacs.org>
License: Apache-2.0
Project-URL: Homepage, https://github.com/barry-scott/CLI-tools
Project-URL: Bug Tracker, https://github.com/barry-scott/CLI-tools/issues
Keywords: development
Classifier: Intended Audience :: End Users/Desktop
Classifier: Topic :: Utilities
Classifier: Environment :: Console
Classifier: Programming Language :: Python :: 3
Requires-Python: >=3.10
License-File: LICENSE
Dynamic: license-file
